fake_random_useragent/__init__.py
fake_random_useragent/core.py
fake_random_useragent-1.0.0.dist-info/METADATA
fake_random_useragent-1.0.0.dist-info/WHEEL
fake_random_useragent-1.0.0.dist-info/top_level.txt
fake_random_useragent-1.0.0.dist-info/RECORD
