Metadata-Version: 2.4
Name: fake-random-useragent
Version: 1.0.0
Summary: A professional random User-Agent generator for web scraping.
Home-page: https://github.com/RidersWeb/Fake-random-userAgent
Author: Viacheslav
Author-email: samara_expert@mail.ru
License: MIT
Keywords: user-agent,fake-useragent,scraper,web-scraping
Classifier: Development Status :: 5 - Production/Stable
Classifier: Programming Language :: Python :: 3
Classifier: Programming Language :: Python :: 3.6
Classifier: Programming Language :: Python :: 3.7
Classifier: Programming Language :: Python :: 3.8
Classifier: Programming Language :: Python :: 3.9
Classifier: Programming Language :: Python :: 3.10
Classifier: Programming Language :: Python :: 3.11
Classifier: Programming Language :: Python :: 3.12
Classifier: License :: OSI Approved :: MIT License
Classifier: Operating System :: OS Independent
Requires-Python: >=3.6
Requires-Dist: importlib-resources>=1.0.0
